{ 
 "nodes": [
{"id":"CSK21", "group": 1, "dark": 0},
{"id":"WEE1", "group": 2, "dark": 0},
{"id":"PAK1", "group": 2, "dark": 0},
{"id":"CHK1", "group": 2, "dark": 0},
{"id":"KS6B1", "group": 2, "dark": 0},
{"id":"MK14", "group": 2, "dark": 0},
{"id":"CSK22", "group": 2, "dark": 0},
{"id":"SRC", "group": 2, "dark": 0},
{"id":"CDK1", "group": 2, "dark": 0},
{"id":"CD11A", "group": 2, "dark": 0},
{"id":"KAPCB", "group": 2, "dark": 0},
{"id":"RIOK2", "group": 2, "dark": 0},
{"id":"PRKDC", "group": 2, "dark": 0},
{"id":"IKKA", "group": 2, "dark": 0},
{"id":"CDK2", "group": 2, "dark": 0},
{"id":"MST4", "group": 2, "dark": 0},
{"id":"TOPK", "group": 2, "dark": 0},
{"id":"CDK4", "group": 2, "dark": 0},
{"id":"EGFR", "group": 2, "dark": 0},
{"id":"MAST3", "group": 2, "dark": 0},
{"id":"AKT1", "group": 2, "dark": 0},
{"id":"MARK3", "group": 2, "dark": 0},
{"id":"MK01", "group": 2, "dark": 0},
{"id":"KC1D", "group": 2, "dark": 0},
{"id":"GSK3B", "group": 2, "dark": 0},
{"id":"STK6", "group": 2, "dark": 0},
{"id":"KPCE", "group": 2, "dark": 0},
{"id":"KSR1", "group": 2, "dark": 0},
{"id":"RIOK1", "group": 2, "dark": 0},
{"id":"KPCZ", "group": 2, "dark": 0},
{"id":"KS6A5", "group": 2, "dark": 0},
{"id":"MK09", "group": 2, "dark": 0},
{"id":"SRPK1", "group": 2, "dark": 0},
{"id":"KS6A4", "group": 2, "dark": 0}],
"links": [ 
{ "source":"WEE1","target":"CSK21","value":1},
{ "source":"PAK1","target":"CSK21","value":1},
{ "source":"CHK1","target":"CSK21","value":1},
{ "source":"CSK21","target":"KS6B1","value":1},
{ "source":"MK14","target":"CSK21","value":1},
{ "source":"CSK22","target":"CSK21","value":1},
{ "source":"CSK21","target":"SRC","value":1},
{ "source":"CSK21","target":"CDK1","value":1},
{ "source":"CD11A","target":"CSK21","value":1},
{ "source":"CSK21","target":"KAPCB","value":1},
{ "source":"RIOK2","target":"CSK21","value":1},
{ "source":"CSK21","target":"PRKDC","value":1},
{ "source":"CSK21","target":"IKKA","value":1},
{ "source":"CDK2","target":"CSK21","value":1},
{ "source":"MST4","target":"CSK21","value":1},
{ "source":"TOPK","target":"CSK21","value":1},
{ "source":"CDK4","target":"CSK21","value":1},
{ "source":"EGFR","target":"CSK21","value":1},
{ "source":"MAST3","target":"CSK21","value":1},
{ "source":"CSK21","target":"AKT1","value":1},
{ "source":"CSK21","target":"MARK3","value":1},
{ "source":"CSK21","target":"MK01","value":1},
{ "source":"CSK21","target":"KC1D","value":1},
{ "source":"CSK21","target":"GSK3B","value":1},
{ "source":"STK6","target":"CSK21","value":1},
{ "source":"KPCE","target":"CSK21","value":1},
{ "source":"KSR1","target":"CSK21","value":1},
{ "source":"RIOK1","target":"CSK21","value":1},
{ "source":"CSK21","target":"KPCZ","value":1},
{ "source":"CSK21","target":"KS6A5","value":1},
{ "source":"CSK21","target":"MK09","value":1},
{ "source":"CSK21","target":"SRPK1","value":1},
{ "source":"CSK21","target":"KS6A4","value":1}] 
 }
