{ 
 "nodes": [
{"id":"FGFR3", "group": 1, "dark": 0},
{"id":"FAK2", "group": 2, "dark": 0},
{"id":"EPHA4", "group": 2, "dark": 0},
{"id":"KPYM", "group": 2, "dark": 0},
{"id":"PDPK1", "group": 2, "dark": 0},
{"id":"JAK2", "group": 2, "dark": 0},
{"id":"EGFR", "group": 2, "dark": 0},
{"id":"ERBB2", "group": 2, "dark": 0},
{"id":"FYN", "group": 2, "dark": 0},
{"id":"PGFRB", "group": 2, "dark": 0},
{"id":"KIT", "group": 2, "dark": 0},
{"id":"FGFR1", "group": 2, "dark": 0},
{"id":"BRAF", "group": 2, "dark": 0},
{"id":"PGFRA", "group": 2, "dark": 0},
{"id":"FGFR2", "group": 2, "dark": 0},
{"id":"ERBB3", "group": 2, "dark": 0},
{"id":"FGFR4", "group": 2, "dark": 0},
{"id":"JAK1", "group": 2, "dark": 0},
{"id":"MK03", "group": 2, "dark": 0},
{"id":"MK01", "group": 2, "dark": 0},
{"id":"TIE2", "group": 2, "dark": 0},
{"id":"KCC2B", "group": 2, "dark": 0},
{"id":"KCC2G", "group": 2, "dark": 0},
{"id":"KCC2D", "group": 2, "dark": 0},
{"id":"ERBB4", "group": 2, "dark": 0},
{"id":"TRIB3", "group": 2, "dark": 0},
{"id":"KCC2A", "group": 2, "dark": 0},
{"id":"AKT2", "group": 2, "dark": 0},
{"id":"FAK1", "group": 2, "dark": 0},
{"id":"CHK1", "group": 2, "dark": 0},
{"id":"ROCK2", "group": 2, "dark": 0},
{"id":"IGF1R", "group": 2, "dark": 0},
{"id":"GSK3B", "group": 2, "dark": 0},
{"id":"KS6A3", "group": 2, "dark": 0}],
"links": [ 
{ "source":"FAK2","target":"FGFR3","value":1},
{ "source":"EPHA4","target":"FGFR3","value":1},
{ "source":"FGFR3","target":"KPYM","value":1},
{ "source":"PDPK1","target":"FGFR3","value":1},
{ "source":"JAK2","target":"FGFR3","value":1},
{ "source":"EGFR","target":"FGFR3","value":1},
{ "source":"ERBB2","target":"FGFR3","value":1},
{ "source":"FYN","target":"FGFR3","value":1},
{ "source":"PGFRB","target":"FGFR3","value":1},
{ "source":"KIT","target":"FGFR3","value":1},
{ "source":"FGFR1","target":"FGFR3","value":1},
{ "source":"BRAF","target":"FGFR3","value":1},
{ "source":"PGFRA","target":"FGFR3","value":1},
{ "source":"FGFR2","target":"FGFR3","value":1},
{ "source":"ERBB3","target":"FGFR3","value":1},
{ "source":"FGFR4","target":"FGFR3","value":1},
{ "source":"FGFR3","target":"JAK1","value":1},
{ "source":"FGFR3","target":"MK03","value":1},
{ "source":"FGFR3","target":"MK01","value":1},
{ "source":"FGFR3","target":"TIE2","value":1},
{ "source":"FGFR3","target":"KCC2B","value":1},
{ "source":"FGFR3","target":"KCC2G","value":1},
{ "source":"FGFR3","target":"KCC2D","value":1},
{ "source":"FGFR3","target":"ERBB4","value":1},
{ "source":"FGFR3","target":"TRIB3","value":1},
{ "source":"FGFR3","target":"KCC2A","value":1},
{ "source":"AKT2","target":"FGFR3","value":1},
{ "source":"FAK1","target":"FGFR3","value":1},
{ "source":"FGFR3","target":"CHK1","value":1},
{ "source":"FGFR3","target":"ROCK2","value":1},
{ "source":"FGFR3","target":"IGF1R","value":1},
{ "source":"FGFR3","target":"GSK3B","value":1},
{ "source":"FGFR3","target":"KS6A3","value":1}] 
 }
