{ 
 "nodes": [
{"id":"KC1D", "group": 1, "dark": 0},
{"id":"CDK5", "group": 2, "dark": 0},
{"id":"KPCD2", "group": 2, "dark": 0},
{"id":"ULK2", "group": 2, "dark": 0},
{"id":"VGFR2", "group": 2, "dark": 0},
{"id":"ATM", "group": 2, "dark": 0},
{"id":"KC1E", "group": 2, "dark": 0},
{"id":"KC1A", "group": 2, "dark": 0},
{"id":"LRRK2", "group": 2, "dark": 0},
{"id":"KAPCA", "group": 2, "dark": 0},
{"id":"PLK4", "group": 2, "dark": 0},
{"id":"STK6", "group": 2, "dark": 0},
{"id":"NEK2", "group": 2, "dark": 0},
{"id":"PLK1", "group": 2, "dark": 0},
{"id":"TTBK2", "group": 2, "dark": 0},
{"id":"MARK4", "group": 2, "dark": 0},
{"id":"TGFR1", "group": 2, "dark": 0},
{"id":"CSK21", "group": 2, "dark": 0},
{"id":"RIOK1", "group": 2, "dark": 0},
{"id":"RIOK2", "group": 2, "dark": 0},
{"id":"E2AK4", "group": 2, "dark": 0},
{"id":"PAK1", "group": 2, "dark": 0},
{"id":"PI3R4", "group": 2, "dark": 0}],
"links": [ 
{ "source":"KC1D","target":"CDK5","value":1},
{ "source":"KC1D","target":"KPCD2","value":1},
{ "source":"ULK2","target":"KC1D","value":1},
{ "source":"KC1D","target":"VGFR2","value":1},
{ "source":"ATM","target":"KC1D","value":1},
{ "source":"KC1E","target":"KC1D","value":1},
{ "source":"KC1A","target":"KC1D","value":1},
{ "source":"LRRK2","target":"KC1D","value":1},
{ "source":"KAPCA","target":"KC1D","value":1},
{ "source":"KC1D","target":"PLK4","value":1},
{ "source":"KC1D","target":"STK6","value":1},
{ "source":"KC1D","target":"NEK2","value":1},
{ "source":"KC1D","target":"PLK1","value":1},
{ "source":"KC1D","target":"TTBK2","value":1},
{ "source":"KC1D","target":"MARK4","value":1},
{ "source":"TGFR1","target":"KC1D","value":1},
{ "source":"CSK21","target":"KC1D","value":1},
{ "source":"RIOK1","target":"KC1D","value":1},
{ "source":"RIOK2","target":"KC1D","value":1},
{ "source":"E2AK4","target":"KC1D","value":1},
{ "source":"KC1D","target":"PAK1","value":1},
{ "source":"KC1D","target":"PI3R4","value":1}] 
 }
